{
  "date": "2026-04-10",
  "title": "2 242/2569 กกต. เห็นชอบแผนการจัดการเลือกตั้งสมาชิกสภากรุงเทพมหานครผู้ว่าราชการ",
  "summary": "หน้า 1/90: รวมข่าว กกต. | ภาพกิจกรรมรอบรั้ว กกต. | หรือข้อโต้แย้ง ในส่วนของฝ่ายกิจการกรรมการการเลือกตั้ง 1 | คณะกรรมการการเลือกตั้ง ครั้งที่ 2/2569 | ข่าว สนง.กกต. (Press Release)\n\nหน้า 2/90: รวมข่าว กกต. | 9 หนังสือพิมพ์ไทยโพสต์ ยื่นหลักฐาน กกต. เพิ่ม ข้อมูลผู้มีสิทธิรั่วไหล! 21\n\nหน้า 3/90: ภาพกิจกรรม รอบรั้ว กกต.",
  "tier": "strict",
  "important": true,
  "matched_keywords": [
    "ผู้ว่าราชการกรุงเทพมหานคร",
    "สมาชิกสภากรุงเทพ",
    "สมาชิกสภากรุงเทพมหานคร",
    "สภากรุงเทพมหานคร",
    "เลือกตั้งสมาชิกสภากรุงเทพ",
    "วันเลือกตั้ง",
    "ค่าใช้จ่าย",
    "กรุงเทพมหานคร",
    "เลือกตั้ง",
    "เลือกตั้งท้องถิ่น",
    "ท้องถิ่น",
    "สมาชิกสภาท้องถิ่น",
    "ผู้บริหารท้องถิ่น",
    "กกต."
  ],
  "finding_count": 35,
  "pdf_url": "https://www.ect.go.th/web-upload/1xff0d34e409a13ef56eea54c52a291126/m_document/2703/31662/file_download/6d26211f84e4ef33bb462ef3344b43df.pdf",
  "pdf_size_mb": 28.43,
  "pdf_pages": 90,
  "source_url": "https://www.ect.go.th/ect_th/th/dailynews2569",
  "pdf_local": "data/ect-news/pdfs/2026-04-10.pdf",
  "images": [
    "data/ect-news/images/2026-04-10/p001.png",
    "data/ect-news/images/2026-04-10/p009.png",
    "data/ect-news/images/2026-04-10/p014.png"
  ]
}